Metadata-Version: 1.1
Name: colorscale
Version: 0.8.2
Summary: Python package to convert images from grayscale to false color and back
Home-page: https://github.com/pklaus/python_colorscale
Author: Philipp Klaus
Author-email: philipp.l.klaus@web.de
License: GPL
Keywords: False color colorscale colormap color map
Platform: any
Classifier: Development Status :: 4 - Beta
Classifier: Operating System :: OS Independent
Classifier: License :: OSI Approved :: GNU General Public License v3 or later (GPLv3+)
Classifier: Programming Language :: Python
Classifier: Programming Language :: Python :: 3
Classifier: Topic :: Scientific/Engineering :: Visualization
